{
    "name": "Electron",
    "fields": [
        {
            "fieldName": "name",
            "fieldType": "String",
            "fieldValidateRules": [
                "required",
                "minlength",
                "maxlength"
            ],
            "fieldValidateRulesMinlength": 1,
            "fieldValidateRulesMaxlength": 32
        }
    ],
    "relationships": [
        {
            "relationshipType": "one-to-many",
            "relationshipName": "particle",
            "otherEntityName": "particle",
            "otherEntityRelationshipName": "electron"
        }
    ],
    "changelogDate": "20190324022901",
    "entityTableName": "electron",
    "dto": "mapstruct",
    "pagination": "no",
    "service": "serviceClass",
    "jpaMetamodelFiltering": false,
    "fluentMethods": true,
    "clientRootFolder": "",
    "applications": "*"
}